pyo3_option_pricing/__init__.py
pyo3_option_pricing/_rust.cpython-310-x86_64-linux-gnu.so
pyo3_option_pricing-0.1.0.dist-info/METADATA
pyo3_option_pricing-0.1.0.dist-info/WHEEL
pyo3_option_pricing-0.1.0.dist-info/top_level.txt
pyo3_option_pricing-0.1.0.dist-info/RECORD
